swinggen.py
swinggen-0.1.2.dist-info/LICENSE.txt
swinggen-0.1.2.dist-info/METADATA
swinggen-0.1.2.dist-info/WHEEL
swinggen-0.1.2.dist-info/top_level.txt
swinggen-0.1.2.dist-info/RECORD
