Metadata-Version: 2.1
Name: swinggen
Version: 0.1.2
Summary: UNKNOWN
Home-page: https://github.com/JonasFovea/swing-trajectory-generator
Author: Jonas Grube
Author-email: jonas.grube@fh-bielefeld.de
License: UNKNOWN
Platform: UNKNOWN
Classifier: Programming Language :: Python :: 3
Classifier: Programming Language :: Python :: 3.6
Classifier: Programming Language :: Python :: 3.7
Classifier: Programming Language :: Python :: 3.8
Classifier: Programming Language :: Python :: 3.9
Classifier: Programming Language :: Python :: 3.10
Classifier: Operating System :: OS Independent
License-File: LICENSE.txt
Requires-Dist: numpy (>=1.8)
Requires-Dist: matplotlib (>=3.0.0)
Provides-Extra: dev
Requires-Dist: pytest (>=3.7) ; extra == 'dev'
